Workbook
Name cc: [1]real!$D$5:$D$15
Name cc: #REF!
Name DEMOLIÇÕES: Aux!$C$15:$C$23
Name ESQUADRIAS: Aux!$H$15
Name ESTRUTURAEDECONCRETOARMADO: Aux!$D$15:$D$16
Name fam: [2]familias!$B$3:$B$11
Name fam: familias!$B$3:$B$11
Name familias: #REF!
Name familias: #REF!
Name familias: Aux!$B$14:$J$14
Name INSTALAÇÕES: Aux!$F$15:$F$19
Name LOUÇASEMETAISEACABAMENTOSELÉTRICOS: Aux!$I$15:$I$16
Name MOBILIZAÇÃOEACOMPANHAMENTOTÉCNICO: Aux!$B$15:$B$17
Name OBRACIVIL: Aux!$E$15:$E$24
Name PINTURA: Aux!$J$15:$J$18
Name REVESTIMENTODEPISOEPAREDES: Aux!$G$15:$G$19
Name REVESTIMENTOSDEPISOEPAREDES: Aux!$G$15:$G$19

Sheet familias
B2: familias
B3: MOBILIZAÇÃO E ACOMPANHAMENTO TÉCNICO
B4: DEMOLIÇÕES
B5: OBRA CIVIL
B6: INSTALAÇÕES
B7: ESQUADRIAS
B8: REVESTIMENTOS DE PISO E PAREDES
B9: LOUÇAS, METAIS E ACABAMENTOS ELÉTRICOS
B10: PINTURA

Sheet aditivos
B2: MATERIAL EXTRA | K2: =SUM(K4:K266) -> 0
B3: DATA DE RECEBIMENTO | C3: QUINZENA | D3: FORNECEDOR | E3: QTD | F3: UNID. | G3: DESCRIÇÃO | H3: MARCA | I3: CENTRO DE CUSTO | J3: NÚMERO NF | K3: VALOR

Sheet lançamentos
A2: MATERIAL | B2: INSUMOS | K2: VENDA
A3: MÃO DE OBRA | B3: # | C3: DATA CUSTO | D3: FORNECEDOR | E3: MAT ou MDO | F3: CENTRO DE CUSTO - FAMILIA | G3: CENTRO DE CUSTO - SUB FAMILIA | H3: NÚMERO NF | I3: VALOR
B4: 1 | C4: 45912 | D4: BAZAR TODA OBRA | E4: MAT | F4: OBRA CIVIL | G4: ELEVAÇÃO DE ALVENARIA | I4: 21.9
B5: =B4+1 -> 2 | C5: 45912 | D5: A ILUMINADA | E5: MAT | F5: INSTALAÇÕES | G5: INSTALAÇÃO ELÉTRICA | I5: 3216.39
B6: =B5+1 -> 3 | C6: 45912 | D6: EDSON SANTOS MATERIAL | E6: MAT | F6: INSTALAÇÕES | G6: INSTALAÇÃO HIDRÁULICA | I6: 30
B7: =B6+1 -> 4 | C7: 45912 | D7: EDSON SANTOS MATERIAL | E7: MAT | F7: INSTALAÇÕES | G7: INSTALAÇÃO HIDRÁULICA | I7: 38.75
B8: =B7+1 -> 5 | C8: 45912 | D8: ÁGUAS CLARA | E8: MAT | F8: MOBILIZAÇÃO E ACOMPANHAMENTO TÉCNICO | G8: OUTROS | I8: 36
B9: =B8+1 -> 6 | C9: 45912 | D9: ZAMACON | E9: MAT | F9: DEMOLIÇÕES | G9: DEMOLIÇÃO DE ALVENARIA | H9: 33745 | I9: 240
B10: =B9+1 -> 7 | C10: 45912 | D10: ZAMACON | E10: MAT | F10: OBRA CIVIL | G10: ELEVAÇÃO DE ALVENARIA | H10: 33745 | I10: 1058.5
B11: =B10+1 -> 8 | C11: 45912 | D11: AL GOSTO | E11: MAT | F11: MOBILIZAÇÃO E ACOMPANHAMENTO TÉCNICO | G11: OUTROS | I11: 60
B12: =B11+1 -> 9 | C12: 45912 | D12: ZAMACON | E12: MAT | F12: MOBILIZAÇÃO E ACOMPANHAMENTO TÉCNICO | G12: EQUIPAMENTOS, EPIS E EPCS | H12: 33745 | I12: 916.8
B13: =B12+1 -> 10 | C13: 45915 | D13: ZAMACON | E13: MAT | F13: OBRA CIVIL | G13: ELEVAÇÃO DE ALVENARIA | H13: 33796 | I13: =1492.8-285-158.8 -> 1049
B14: =B13+1 -> 11 | C14: 45915 | D14: ZAMACON | E14: MAT | F14: DEMOLIÇÕES | G14: ABERTURA DE RASGOS DIVERSOS EM ALVENARIA E CONTRAPISO | H14: 33796 | I14: =45+240 -> 285
B15: =B14+1 -> 12 | C15: 45915 | D15: ZAMACON | E15: MAT | F15: INSTALAÇÕES | G15: INSTALAÇÃO ELÉTRICA | H15: 33796 | I15: =84+30+13.8+13+18 -> 158.8
B16: =B15+1 -> 13 | C16: 45917 | D16: ÁGUAS CLARA | E16: MAT | F16: MOBILIZAÇÃO E ACOMPANHAMENTO TÉCNICO | G16: OUTROS | I16: 14
B17: =B16+1 -> 14 | C17: 45918 | D17: EDSON SANTOS MATERIAL | E17: MAT | F17: OBRA CIVIL | G17: ELEVAÇÃO DE ALVENARIA | I17: 12.8
B18: =B17+1 -> 15 | C18: 45918 | D18: ZAMACON | E18: MAT | F18: OBRA CIVIL | G18: ELEVAÇÃO DE ALVENARIA | H18: 33858 | I18: 153
B19: =B18+1 -> 16 | C19: 45918 | D19: ZAMACON | E19: MAT | F19: INSTALAÇÕES | G19: INSTALAÇÃO ELÉTRICA | H19: 33858 | I19: =225+215 -> 440
B20: =B19+1 -> 17 | C20: 45918 | D20: ZAMACON | E20: MAT | F20: MOBILIZAÇÃO E ACOMPANHAMENTO TÉCNICO | G20: EQUIPAMENTOS, EPIS E EPCS | H20: 33858 | I20: 74
B21: =B20+1 -> 18 | C21: 45922 | D21: ÁGUAS CLARA | E21: MAT | F21: MOBILIZAÇÃO E ACOMPANHAMENTO TÉCNICO | G21: OUTROS | I21: 14
B22: =B21+1 -> 19 | C22: 45922 | D22: MENON GRÁFICA | E22: MAT | F22: MOBILIZAÇÃO E ACOMPANHAMENTO TÉCNICO | G22: OUTROS | I22: 39.8
B23: =B22+1 -> 20 | C23: 45923 | D23: ACASA DRYWALL | E23: MAT | F23: OBRA CIVIL | G23: INSTALAÇÃO DE FORRO DE GESSO COM TABICAS NOS BANHEIROS | I23: 456.5
B24: =B23+1 -> 21 | C24: 45923 | D24: ZAMACON | E24: MAT | F24: OBRA CIVIL | G24: ELEVAÇÃO DE ALVENARIA | H24: 33935 | I24: 472.2
B25: =B24+1 -> 22 | C25: 45924 | D25: OBRAMAX | E25: MAT | F25: OBRA CIVIL | G25: ELEVAÇÃO DE ALVENARIA | I25: 458.12
B26: =B25+1 -> 23 | C26: 45925 | D26: LUIS ENCARREGADO | E26: MDO | F26: DEMOLIÇÕES | G26: DEMOLIÇÃO DE ALVENARIA | I26: =340*10 -> 3400
B27: =B26+1 -> 24 | C27: 45925 | D27: ANDRÉ AJUDANTE | E27: MDO | F27: DEMOLIÇÕES | G27: DEMOLIÇÃO DE ALVENARIA | I27: =160*10 -> 1600
B28: =B27+1 -> 25 | C28: 45925 | D28: MARLON AJUDANTE | E28: MDO | F28: DEMOLIÇÕES | G28: DEMOLIÇÃO DE ALVENARIA | I28: =160*10 -> 1600
B29: =B28+1 -> 26 | C29: 45926 | D29: ÁGUAS CLARA | E29: MAT | F29: MOBILIZAÇÃO E ACOMPANHAMENTO TÉCNICO | G29: OUTROS | I29: 15
B30: =B29+1 -> 27 | C30: 45926 | D30: ZAMACON | E30: MAT | F30: OBRA CIVIL | G30: ELEVAÇÃO DE ALVENARIA | H30: 33985 | I30: 259.5
B31: =B30+1 -> 28 | C31: 45926 | D31: CONSTRUX | E31: MAT | F31: OBRA CIVIL | G31: ELEVAÇÃO DE ALVENARIA | H31: 11279 | I31: 708
B32: =B31+1 -> 29 | C32: 45929 | D32: OBRAMAX | E32: MAT | F32: ESTRUTURA E DE CONCRETO ARMADO | G32: EXECUÇÃO DE ESCADA DE CONCRETO ARMADO | I32: 1236.76
B33: =B32+1 -> 30 | C33: 45929 | D33: ELETROMIL | E33: MAT | F33: INSTALAÇÕES | G33: INSTALAÇÃO ELÉTRICA | I33: 1203.56
B34: =B33+1 -> 31 | C34: 45929 | D34: LUIS ENCARREGADO | E34: MDO | F34: DEMOLIÇÕES | G34: DEMOLIÇÃO DE ALVENARIA | I34: =340*1 -> 340
B35: =B34+1 -> 32 | C35: 45929 | D35: ANDRÉ AJUDANTE | E35: MDO | F35: DEMOLIÇÕES | G35: DEMOLIÇÃO DE ALVENARIA | I35: =160*1 -> 160
B36: =B35+1 -> 33 | C36: 45929 | D36: MARLON AJUDANTE | E36: MDO | F36: DEMOLIÇÕES | G36: DEMOLIÇÃO DE ALVENARIA | I36: =160*1 -> 160
B37: =B36+1 -> 34 | C37: 45930 | D37: ZAMACON | E37: MAT | F37: OBRA CIVIL | G37: ELEVAÇÃO DE ALVENARIA | H37: 34026 | I37: 221.4
B38: =B37+1 -> 35 | C38: 45930 | D38: LUCAS RIBEIRO | E38: MDO | F38: MOBILIZAÇÃO E ACOMPANHAMENTO TÉCNICO | G38: ACOMPANHAMENTO TÉCNICO | I38: 51.7
B39: =B38+1 -> 36 | C39: 45930 | D39: TUCA | E39: MDO | F39: MOBILIZAÇÃO E ACOMPANHAMENTO TÉCNICO | G39: ACOMPANHAMENTO TÉCNICO | I39: 314.3
B40: =B39+1 -> 37 | C40: 45931 | D40: ÁGUAS CLARA | E40: MAT | F40: MOBILIZAÇÃO E ACOMPANHAMENTO TÉCNICO | G40: OUTROS | I40: 15
B41: =B40+1 -> 38 | C41: 45931 | D41: ACASA DRYWALL | E41: MAT | F41: OBRA CIVIL | G41: INSTALAÇÃO DE FORRO DE GESSO COM TABICAS NOS BANHEIROS | I41: 2970.65
B42: =B41+1 -> 39 | C42: 45933 | D42: MENON GRÁFICA | E42: MAT | F42: MOBILIZAÇÃO E ACOMPANHAMENTO TÉCNICO | G42: OUTROS | I42: 50
B43: =B42+1 -> 40 | C43: 45936 | D43: ZAMACON | E43: MAT | F43: OBRA CIVIL | G43: ELEVAÇÃO DE ALVENARIA | H43: 34132 | I43: 673.5
B44: =B43+1 -> 41 | C44: 45936 | D44: RESERVA MADEIRAS | E44: MAT | F44: ESTRUTURA E DE CONCRETO ARMADO | G44: EXECUÇÃO DE ESCADA DE CONCRETO ARMADO | I44: 711.9
B45: =B44+1 -> 42 | C45: 45936 | D45: RESERVA MADEIRAS | E45: MAT | F45: ESTRUTURA E DE CONCRETO ARMADO | G45: EXECUÇÃO DE ESCADA DE CONCRETO ARMADO | I45: 221.25
B46: =B45+1 -> 43 | C46: 45938 | D46: ÁGUAS CLARA | E46: MAT | F46: MOBILIZAÇÃO E ACOMPANHAMENTO TÉCNICO | G46: OUTROS | I46: 15
B47: =B46+1 -> 44 | C47: 45939 | D47: ZAMACON | E47: MAT | F47: ESTRUTURA E DE CONCRETO ARMADO | G47: EXECUÇÃO DE ESCADA DE CONCRETO ARMADO | H47: 34210 | I47: 499.7
B48: =B47+1 -> 45 | C48: 45939 | D48: CONSTRUX | E48: MAT | F48: ESTRUTURA E DE CONCRETO ARMADO | G48: EXECUÇÃO DE ESCADA DE CONCRETO ARMADO | H48: 11296 | I48: 333
B49: =B48+1 -> 46 | C49: 45939 | D49: LOC NAVE | E49: MAT | F49: MOBILIZAÇÃO E ACOMPANHAMENTO TÉCNICO | G49: EQUIPAMENTOS, EPIS E EPCS | I49: 650
B50: =B49+1 -> 47 | C50: 45940 | D50: EDSON SANTOS MATERIAL | E50: MAT | F50: ESTRUTURA E DE CONCRETO ARMADO | G50: EXECUÇÃO DE ESCADA DE CONCRETO ARMADO | I50: 48.9
B51: =B50+1 -> 48 | C51: 45940 | D51: EDSON SANTOS MATERIAL | E51: MAT | F51: ESTRUTURA E DE CONCRETO ARMADO | G51: EXECUÇÃO DE ESCADA DE CONCRETO ARMADO | I51: 29.9
B52: =B51+1 -> 49 | C52: 45940 | D52: LUIS ENCARREGADO | E52: MDO | F52: OBRA CIVIL | G52: ELEVAÇÃO DE ALVENARIA | I52: =340*10 -> 3400
B53: =B52+1 -> 50 | C53: 45940 | D53: ANDRÉ AJUDANTE | E53: MDO | F53: OBRA CIVIL | G53: ELEVAÇÃO DE ALVENARIA | I53: =160*10 -> 1600
B54: =B53+1 -> 51 | C54: 45940 | D54: MARLON AJUDANTE | E54: MDO | F54: OBRA CIVIL | G54: ELEVAÇÃO DE ALVENARIA | I54: =160*10 -> 1600
B55: =B54+1 -> 52 | C55: 45943 | D55: AL GOSTO | E55: MAT | F55: MOBILIZAÇÃO E ACOMPANHAMENTO TÉCNICO | G55: OUTROS | I55: 61
B56: =B55+1 -> 53 | C56: 45943 | D56: CAFÉ DA MANHÃ | E56: MAT | F56: MOBILIZAÇÃO E ACOMPANHAMENTO TÉCNICO | G56: OUTROS | I56: 14
B57: =B56+1 -> 54 | C57: 45944 | D57: KING OURO | E57: MAT | F57: INSTALAÇÕES | G57: INSTALAÇÃO ELÉTRICA | I57: 2647.35
B58: =B57+1 -> 55 | C58: 45944 | D58: MEG RIO ENTULHOS | E58: MAT | F58: DEMOLIÇÕES | G58: BOTA FORA EM CAÇAMBAS LEGAIS | I58: 800
B59: =B58+1 -> 56 | C59: 45945 | D59: ÁGUAS CLARA | E59: MAT | F59: MOBILIZAÇÃO E ACOMPANHAMENTO TÉCNICO | G59: OUTROS | I59: 14
B60: =B59+1 -> 57 | C60: 45945 | D60: ZAMACON | E60: MAT | F60: INSTALAÇÕES | G60: INSTALAÇÃO ELÉTRICA | H60: 34337 | I60: 887.5
B61: =B60+1 -> 58 | C61: 45946 | D61: MEGABOR | E61: MAT | F61: MOBILIZAÇÃO E ACOMPANHAMENTO TÉCNICO | G61: EQUIPAMENTOS, EPIS E EPCS | I61: 400
B62: =B61+1 -> 59 | C62: 45953 | D62: ZAMACON | E62: MAT | F62: INSTALAÇÕES | G62: INSTALAÇÃO HIDRÁULICA | H62: 34454 | I62: 663.2
B63: =B62+1 -> 60 | C63: 45954 | D63: ÁGUAS CLARA | E63: MAT | F63: MOBILIZAÇÃO E ACOMPANHAMENTO TÉCNICO | G63: OUTROS | I63: 14
B64: =B63+1 -> 61 | C64: 45954 | D64: LUIS ENCARREGADO | E64: MDO | F64: OBRA CIVIL | G64: ELEVAÇÃO DE ALVENARIA | I64: =340*9 -> 3060
B65: =B64+1 -> 62 | C65: 45954 | D65: ANDRÉ AJUDANTE | E65: MDO | F65: OBRA CIVIL | G65: ELEVAÇÃO DE ALVENARIA | I65: =160*9 -> 1440
B66: =B65+1 -> 63 | C66: 45954 | D66: MARLON AJUDANTE | E66: MDO | F66: OBRA CIVIL | G66: ELEVAÇÃO DE ALVENARIA | I66: =160*9 -> 1440
B67: =B66+1 -> 64 | C67: 45957 | D67: A ILUMINADA | E67: MAT | F67: INSTALAÇÕES | G67: INSTALAÇÃO ELÉTRICA | I67: 1689.14
B68: =B67+1 -> 65 | C68: 45957 | D68: ZAMACON | E68: MAT | F68: OBRA CIVIL | G68: ELEVAÇÃO DE ALVENARIA | H68: 34527 | I68: 145
B69: =B68+1 -> 66 | C69: 45957 | D69: ZAMACON | E69: MAT | F69: INSTALAÇÕES | G69: INSTALAÇÃO ELÉTRICA | H69: 34527 | I69: 195
B70: =B69+1 -> 67 | C70: 45957 | D70: ZAMACON | E70: MAT | F70: REVESTIMENTOS DE PISO E PAREDES | H70: 34527 | I70: 153
B71: =B70+1 -> 68 | C71: 45957 | D71: BARRAQUINHA SALGADO | E71: MAT | F71: MOBILIZAÇÃO E ACOMPANHAMENTO TÉCNICO | G71: OUTROS | I71: 12
B72: =B71+1 -> 69 | C72: 45958 | D72: ÁGUAS CLARA | E72: MAT | F72: MOBILIZAÇÃO E ACOMPANHAMENTO TÉCNICO | G72: OUTROS | I72: 15
B73: =B72+1 -> 70 | C73: 45958 | D73: RESERVA MADEIRAS | E73: MAT | F73: ESTRUTURA E DE CONCRETO ARMADO | G73: EXECUÇÃO DE ESCADA DE CONCRETO ARMADO | I73: 277.2
B74: =B73+1 -> 71 | C74: 45959 | D74: CONSTRUX | E74: MAT | F74: OBRA CIVIL | G74: ELEVAÇÃO DE ALVENARIA | H74: 11317 | I74: 156.5
B75: =B74+1 -> 72 | C75: 45960 | D75: ZAMACON | E75: MAT | F75: OBRA CIVIL | G75: ELEVAÇÃO DE ALVENARIA | H75: 34582 | I75: 131.7
B76: =B75+1 -> 73 | C76: 45960 | D76: HIDRO JÁ | E76: MAT | F76: INSTALAÇÕES | G76: INSTALAÇÃO HIDRÁULICA | H76: 27793 | I76: 192.59
B77: =B76+1 -> 74 | C77: 45960 | D77: OBRAMAX | E77: MAT | F77: INSTALAÇÕES | G77: INSTALAÇÃO HIDRÁULICA | I77: 713.72
B78: =B77+1 -> 75 | C78: 45964 | D78: LEROY MERLIN | E78: MAT | F78: REVESTIMENTOS DE PISO E PAREDES | I78: 573.75
B79: =B78+1 -> 76 | C79: 45965 | D79: ZAMACON | E79: MAT | F79: OBRA CIVIL | G79: ELEVAÇÃO DE ALVENARIA | H79: 34654 | I79: 208
B80: =B79+1 -> 77 | C80: 45968 | D80: ÁGUAS CLARA | E80: MAT | F80: MOBILIZAÇÃO E ACOMPANHAMENTO TÉCNICO | G80: OUTROS | I80: 15
B81: =B80+1 -> 78 | C81: 45968 | D81: LUIS ENCARREGADO | E81: MDO | F81: OBRA CIVIL | G81: ELEVAÇÃO DE ALVENARIA | I81: =340*10 -> 3400
B82: =B81+1 -> 79 | C82: 45968 | D82: ANDRÉ AJUDANTE | E82: MDO | F82: OBRA CIVIL | G82: ELEVAÇÃO DE ALVENARIA | I82: =160*10 -> 1600
B83: =B82+1 -> 80 | C83: 45971 | D83: ZAMACON | E83: MAT | F83: OBRA CIVIL | G83: ELEVAÇÃO DE ALVENARIA | H83: 34784 | I83: 120
B84: =B83+1 -> 81 | C84: 45972 | D84: A ILUMINADA | E84: MAT | F84: INSTALAÇÕES | G84: INSTALAÇÃO ELÉTRICA | I84: 1982.6
B85: =B84+1 -> 82 | C85: 45972 | D85: LUCAS RIBEIRO | E85: MDO | F85: MOBILIZAÇÃO E ACOMPANHAMENTO TÉCNICO | G85: ACOMPANHAMENTO TÉCNICO | I85: 139.2
B86: =B85+1 -> 83 | C86: 45972 | D86: TUCA | E86: MDO | F86: MOBILIZAÇÃO E ACOMPANHAMENTO TÉCNICO | G86: ACOMPANHAMENTO TÉCNICO | I86: 404.4
B87: =B86+1 -> 84 | C87: 45972 | D87: UBER FLASH | E87: MAT | F87: MOBILIZAÇÃO E ACOMPANHAMENTO TÉCNICO | G87: OUTROS | I87: 17.91
B88: =B87+1 -> 85 | C88: 45973 | D88: ABSOLUT AIR | E88: MAT | F88: INSTALAÇÕES | G88: INSTALAÇÃO DE AR CONDICIONADO | I88: 1873.32
B89: =B88+1 -> 86 | C89: 45973 | D89: OBRAMAX | E89: MAT | F89: INSTALAÇÕES | G89: INSTALAÇÃO ELÉTRICA | I89: 403.81
B90: =B89+1 -> 87 | C90: 45973 | D90: DIBA 695 | E90: MAT | F90: INSTALAÇÕES | G90: INSTALAÇÃO HIDRÁULICA | H90: 229631 | I90: 60.1
B91: =B90+1 -> 88 | C91: 45978 | D91: ÁGUAS CLARA | E91: MAT | F91: MOBILIZAÇÃO E ACOMPANHAMENTO TÉCNICO | G91: OUTROS | I91: 15
B92: =B91+1 -> 89 | C92: 45978 | D92: LANCHONETE | E92: MAT | F92: MOBILIZAÇÃO E ACOMPANHAMENTO TÉCNICO | G92: OUTROS | I92: 22
B93: =B92+1 -> 90 | C93: 45980 | D93: OBRAMAX | E93: MAT | F93: INSTALAÇÕES | G93: INSTALAÇÃO HIDRÁULICA | I93: 49.91
B94: =B93+1 -> 91 | C94: 45981 | D94: AMOEDO | E94: MAT | F94: INSTALAÇÕES | G94: INSTALAÇÃO HIDRÁULICA | I94: 292.58
B95: =B94+1 -> 92 | C95: 45981 | D95: RESTAURANTE | E95: MAT | F95: MOBILIZAÇÃO E ACOMPANHAMENTO TÉCNICO | G95: OUTROS | I95: 43.89
B96: =B95+1 -> 93 | C96: 45985 | D96: ÁGUAS CLARA | E96: MAT | F96: MOBILIZAÇÃO E ACOMPANHAMENTO TÉCNICO | G96: OUTROS | I96: 14
B97: =B96+1 -> 94 | C97: 45985 | D97: A ILUMINADA | E97: MAT | F97: INSTALAÇÕES | G97: INSTALAÇÃO ELÉTRICA | I97: 232
B98: =B97+1 -> 95 | C98: 45986 | D98: UBER FLASH | E98: MAT | F98: INSTALAÇÕES | G98: INSTALAÇÃO DE AR CONDICIONADO | I98: 43.5
B99: =B98+1 -> 96 | C99: 45993 | D99: ÁGUAS CLARA | E99: MAT | F99: MOBILIZAÇÃO E ACOMPANHAMENTO TÉCNICO | G99: OUTROS | I99: 15
B100: =B99+1 -> 97 | C100: 45994 | D100: LUCAS RIBEIRO | E100: MDO | F100: MOBILIZAÇÃO E ACOMPANHAMENTO TÉCNICO | G100: ACOMPANHAMENTO TÉCNICO | I100: 59.7
B101: =B100+1 -> 98 | C101: 45994 | D101: TUCA | E101: MDO | F101: MOBILIZAÇÃO E ACOMPANHAMENTO TÉCNICO | G101: ACOMPANHAMENTO TÉCNICO | I101: 347.7
...

Sheet orçamento
B2: ORÇAMENTO NURBAN
B3: ITEM | C3: DESCRIÇÃO | D3: QUANTIDADE | E3: UNIDADE | F3: % ABC | G3: UNITÁRIO MATERIAL | H3: TOTAL MATERIAL | I3: UNITÁRIO MDO | J3: TOTAL MDO | K3: SUBTOTAL | L3: TOTAL C/ BDI | M3: BDI MAT | N3: BDI MDO | O3: NF | Q3: BDI MAT | R3: BDI MDO | S3: NF
M4: 1.15 | N4: 1.28 | O4: 0.1533 | Q4: 1.15 | R4: 1.28 | S4: 0.1533
B5: 1 | C5: 1. MOBILIZAÇÃO E ACOMPANHAMENTO TÉCNICO | F5: =K5/$K$55 -> 0.19076251 | H5: =SUM(H6:H8) -> 11000 | J5: =SUM(J6:J8) -> 36576 | K5: =J5+H5 -> 47576 | L5: =J5*$N$4+H5*$M$4 -> 59467.28
C6: 1.1 ACOMPANHAMENTO TÉCNICO | D6: 6 | E6: MÊS | F6: =K6/$K$55 -> 0.1466565 | G6: 0 | H6: =D6*G6 -> 0 | I6: 6096 | J6: =I6*D6 -> 36576 | K6: =J6+H6 -> 36576 | L6: =J6*$N$4+H6*$M$4 -> 46817.28
C7: 1.2 EQUIPAMENTOS, EPIS E EPCS | D7: 6 | E7: MÊS | F7: =K7/$K$55 -> 0.036086736 | G7: 1500 | H7: =D7*G7 -> 9000 | I7: 0 | J7: =I7*D7 -> 0 | K7: =J7+H7 -> 9000 | L7: =J7*$N$4+H7*$M$4 -> 10350
C8: 1.3 OUTROS | D8: 1 | E8: VB | F8: =K8/$K$55 -> 0.0080192747 | G8: 2000 | H8: =D8*G8 -> 2000 | I8: 0 | J8: =I8*D8 -> 0 | K8: =J8+H8 -> 2000 | L8: =J8*$N$4+H8*$M$4 -> 2300
B9: =B5+1 -> 2 | C9: 2. DEMOLIÇÕES | F9: =K9/$K$55 -> 0.092237176 | H9: =SUM(H10:H18) -> 8583.6175 | J9: =SUM(J10:J18) -> 14420.253 | K9: =J9+H9 -> 23003.87 | L9: =J9*$N$4+H9*$M$4 -> 28329.083
C10: 2.1 DEMOLIÇÃO DE ALVENARIA | D10: =(0.6+5.37+0.85+0.9+1.37+0.8+1.26+0.8)*2.7*0.15 -> 4.83975 | E10: M³ | F10: =K10/$K$55 -> 0.014748288 | G10: 10 | H10: =D10*G10 -> 48.3975 | I10: 750 | J10: =I10*D10 -> 3629.8125 | K10: =J10+H10 -> 3678.21 | L10: =J10*$N$4+H10*$M$4 -> 4701.8171
C11: 2.2 DEMOLIÇÃO DE PISO | D11: =4.5+3.33+0.98 -> 8.81 | E11: M² | F11: =K11/$K$55 -> 0.0010597471 | G11: 10 | H11: =D11*G11 -> 88.1 | I11: 20 | J11: =I11*D11 -> 176.2 | K11: =J11+H11 -> 264.3 | L11: =J11*$N$4+H11*$M$4 -> 326.851
C12: 2.3 DEMOLIÇÃO DE ESCADA | D12: 1 | E12: VB | F12: =K12/$K$55 -> 0.0080192747 | G12: 1000 | H12: =D12*G12 -> 1000 | I12: 1000 | J12: =I12*D12 -> 1000 | K12: =J12+H12 -> 2000 | L12: =J12*$N$4+H12*$M$4 -> 2430
C13: 2.4 ABERTURA DE VÃO EM LAJE | D13: 1 | E13: VB | F13: =K13/$K$55 -> 0.012028912 | G13: 1500 | H13: =D13*G13 -> 1500 | I13: 1500 | J13: =I13*D13 -> 1500 | K13: =J13+H13 -> 3000 | L13: =J13*$N$4+H13*$M$4 -> 3645
C14: 2.5 ABERTURA DE RASGOS DIVERSOS EM ALVENARIA E CONTRAPISO | D14: 1 | E14: VB | F14: =K14/$K$55 -> 0.020048187 | G14: 1000 | H14: =D14*G14 -> 1000 | I14: 4000 | J14: =I14*D14 -> 4000 | K14: =J14+H14 -> 5000 | L14: =J14*$N$4+H14*$M$4 -> 6270
C15: 2.6 DEMOLIÇÃO DE REVESTIMENTO DE PAREDE | D15: =(1.77+1+1.93+0.85+1.77+1.93+0.75+0.98+2.06*2+1.78*2)*2.7 -> 50.382 | E15: M² | F15: =K15/$K$55 -> 0.0060604065 | G15: 10 | H15: =D15*G15 -> 503.82 | I15: 20 | J15: =I15*D15 -> 1007.64 | K15: =J15+H15 -> 1511.46 | L15: =J15*$N$4+H15*$M$4 -> 1869.1722
C16: 2.7 DEMOLIÇÃO DE FORRO | D16: =D23 -> 39.33 | E16: M² | F16: =K16/$K$55 -> 0.0047309711 | G16: 10 | H16: =D16*G16 -> 393.3 | I16: 20 | J16: =I16*D16 -> 786.6 | K16: =J16+H16 -> 1179.9 | L16: =J16*$N$4+H16*$M$4 -> 1459.143
C17: 2.8 DEMOLIÇÃO DE LOUÇAS, BANCADAS, MARCENARIA E ESQUADRIAS | D17: 18 | E17: UNIDADE | F17: =K17/$K$55 -> 0.0046912757 | G17: 25 | H17: =G17*D17 -> 450 | I17: 40 | J17: =I17*D17 -> 720 | K17: =J17+H17 -> 1170 | L17: =J17*$N$4+H17*$M$4 -> 1439.1
C18: 2.9 BOTA FORA EM CAÇAMBAS LEGAIS | D18: 8 | E18: UNIDADE | F18: =K18/$K$55 -> 0.020850114 | G18: 450 | H18: =G18*D18 -> 3600 | I18: 200 | J18: =I18*D18 -> 1600 | K18: =J18+H18 -> 5200 | L18: =J18*$N$4+H18*$M$4 -> 6188
B19: =B9+1 -> 3 | C19: 3. ESTRUTURA E DE CONCRETO ARMADO | F19: =K19/$K$55 -> 0.038091555 | H19: =SUM(H20:H21) -> 3750 | J19: =SUM(J20:J21) -> 5750 | K19: =J19+H19 -> 9500 | L19: =J19*$N$4+H19*$M$4 -> 11672.5
C20: 3.1 EXECUÇÃO DE ESCADA DE CONCRETO ARMADO | D20: 1 | E20: VB | F20: =K20/$K$55 -> 0.036086736 | G20: 3500 | H20: =D20*G20 -> 3500 | I20: 5500 | J20: =I20*D20 -> 5500 | K20: =J20+H20 -> 9000 | L20: =J20*$N$4+H20*$M$4 -> 11065
C21: 3.2 EXECUÇÃO DE BANCADA EM CONCRETO | D21: 1 | E21: UNIDADE | F21: =K21/$K$55 -> 0.0020048187 | G21: 250 | H21: =D21*G21 -> 250 | I21: 250 | J21: =I21*D21 -> 250 | K21: =J21+H21 -> 500 | L21: =J21*$N$4+H21*$M$4 -> 607.5
B22: =B19+1 -> 4 | C22: 4. OBRA CIVIL | F22: =K22/$K$55 -> 0.19768729 | H22: =SUM(H23:H32) -> 23491.634 | J22: =SUM(J23:J32) -> 25811.4 | K22: =J22+H22 -> 49303.034 | L22: =J22*$N$4+H22*$M$4 -> 60053.971
C23: 4.1 INSTALAÇÃO DE FORRO DE GESSO COM TABICAS NOS BANHEIROS | D23: =3.51+4.5+1.83+3.33+1.65+12.32+12.19 -> 39.33 | E23: M² | F23: =K23/$K$55 -> 0.018608486 | G23: 58 | H23: =D23*G23 -> 2281.14 | I23: 60 | J23: =I23*D23 -> 2359.8 | K23: =J23+H23 -> 4640.94 | L23: =J23*$N$4+H23*$M$4 -> 5643.855
C24: 4.2 INSTALAÇÃO DE CORTINEIROS | D24: =9.33+3.11+1.86+2.29+2.21+2.81+4.69+2.31+4.55+3.98+2.41 -> 39.55 | E24: M | F24: =K24/$K$55 -> 0.01506521 | G24: 35 | H24: =D24*G24 -> 1384.25 | I24: 60 | J24: =I24*D24 -> 2373 | K24: =J24+H24 -> 3757.25 | L24: =J24*$N$4+H24*$M$4 -> 4629.3275
C25: 4.3 ELEVAÇÃO DE DRYWALL | D25: =(0.6*1.02)+(0.6*2.7)+(1.35+0.63+1.79)*1.85*2*1.5+2.7*(0.92+1.1*2+2.54*2)+(4.75+4.08+0.29+0.63+0.29+3.76+7.63+1.68+1.2+2.18+1.28)*3.07 -> 130.5494 | E25: M² | F25: =K25/$K$55 -> 0.060197411 | G25: 55 | H25: =D25*G25 -> 7180.217 | I25: 60 | J25: =I25*D25 -> 7832.964 | K25: =J25+H25 -> 15013.181 | L25: =J25*$N$4+H25*$M$4 -> 18283.443
C26: 4.4 ELEVAÇÃO DE PLACAS CIMENTÍCIAS | D26: =(4.75+4.08+0.29+0.63+0.29+3.76+7.63+1.68+1.2+2.18+1.28)*3.07 -> 85.2539 | E26: M² | F26: =K26/$K$55 -> 0.058112328 | G26: 90 | H26: =D26*G26 -> 7672.851 | I26: 80 | J26: =I26*D26 -> 6820.312 | K26: =J26+H26 -> 14493.163 | L26: =J26*$N$4+H26*$M$4 -> 17553.778
C27: 4.5 REQUADRO DE PORTAS E JANELAS | D27: 4 | E27: M² | F27: =K27/$K$55 -> 0.0028869389 | G27: 60 | H27: =D27*G27 -> 240 | I27: 120 | J27: =I27*D27 -> 480 | K27: =J27+H27 -> 720 | L27: =J27*$N$4+H27*$M$4 -> 890.4
C28: 4.6 CONSTRUÇÃO DE SÓCULOS | D28: =0.48*0.97+1.08*0.48+1.74*0.47+1.38*0.48+0.5*0.96+2.53*0.6 -> 4.4622 | E28: M² | F28: =K28/$K$55 -> 0.0026837706 | G28: 30 | H28: =D28*G28 -> 133.866 | I28: 120 | J28: =I28*D28 -> 535.464 | K28: =J28+H28 -> 669.33 | L28: =J28*$N$4+H28*$M$4 -> 839.33982
C29: 4.7 ELEVAÇÃO DE ALVENARIA | D29: =(0.53+0.6+0.69)*2.7 -> 4.914 | E29: M² | F29: =K29/$K$55 -> 0.0023644029 | G29: 60 | H29: =D29*G29 -> 294.84 | I29: 60 | J29: =I29*D29 -> 294.84 | K29: =J29+H29 -> 589.68 | L29: =J29*$N$4+H29*$M$4 -> 716.4612
C30: 4.8 RECUPERAÇÃO DE CONTRAPISO | D30: =(32+D11)*1.2 -> 48.972 | E30: M² | F30: =K30/$K$55 -> 0.023563195 | G30: 60 | H30: =D30*G30 -> 2938.32 | I30: 60 | J30: =I30*D30 -> 2938.32 | K30: =J30+H30 -> 5876.64 | L30: =J30*$N$4+H30*$M$4 -> 7140.1176 | Q30: =2.7*(0.92+1.1*2+2.54*2) -> 22.14
C31: 4.9 EXECUÇÃO DE EMBOÇO | D31: =D15+D29*2 -> 60.21 | E31: M² | F31: =K31/$K$55 -> 0.010863912 | G31: 15 | H31: =D31*G31 -> 903.15 | I31: 30 | J31: =I31*D31 -> 1806.3 | K31: =J31+H31 -> 2709.45 | L31: =J31*$N$4+H31*$M$4 -> 3350.6865
C32: 4.10 IMPERMEABILIZAÇÃO COM CRISTALIZANTE NOS BANHEIROS | D32: =4.5+1.65+3.33+(1.48*4+2.06*2+1.78*2+1.93*2+2.57*2)*0.4 -> 18.52 | E32: M² | F32: =K32/$K$55 -> 0.0033416318 | G32: 25 | H32: =D32*G32 -> 463 | I32: 20 | J32: =I32*D32 -> 370.4 | K32: =J32+H32 -> 833.4 | L32: =J32*$N$4+H32*$M$4 -> 1006.562
B33: =B22+1 -> 5 | C33: 5. INSTALAÇÕES | F33: =K33/$K$55 -> 0.25621583 | H33: =SUM(H34:H38) -> 21150 | J33: =SUM(J34:J38) -> 42750 | K33: =J33+H33 -> 63900 | L33: =J33*$N$4+H33*$M$4 -> 79042.5
C34: 5.1 INSTALAÇÃO HIDRÁULICA | D34: 6 | E34: A. MOLHADA | F34: =K34/$K$55 -> 0.036086736 | G34: 500 | H34: =D34*G34 -> 3000 | I34: 1000 | J34: =I34*D34 -> 6000 | K34: =J34+H34 -> 9000 | L34: =J34*$N$4+H34*$M$4 -> 11130
C35: 5.2 INSTALAÇÃO ELÉTRICA | D35: 1 | E35: VB | F35: =K35/$K$55 -> 0.14314405 | G35: =2300+1400+6000 -> 9700 | H35: =D35*G35 -> 9700 | I35: 26000 | J35: =I35*D35 -> 26000 | K35: =J35+H35 -> 35700 | L35: =J35*$N$4+H35*$M$4 -> 44435
C36: 5.3 INSTALAÇÕES ESPECIAIS | D36: 1 | E36: VB | F36: =K36/$K$55 -> 0.032478062 | G36: =1800+1300+1000 -> 4100 | H36: =D36*G36 -> 4100 | I36: 4000 | J36: =I36*D36 -> 4000 | K36: =J36+H36 -> 8100 | L36: =J36*$N$4+H36*$M$4 -> 9835
C37: 5.4 INSTALAÇÃO GÁS | D37: 1 | E37: VB | F37: =K37/$K$55 -> 0.0044106011 | G37: 350 | H37: =D37*G37 -> 350 | I37: 750 | J37: =I37*D37 -> 750 | K37: =J37+H37 -> 1100 | L37: =J37*$N$4+H37*$M$4 -> 1362.5
C38: 5.5 INSTALAÇÃO DE AR CONDICIONADO | D38: 8 | E38: UNIDADE | F38: =K38/$K$55 -> 0.040096373 | G38: 500 | H38: =D38*G38 -> 4000 | I38: 750 | J38: =I38*D38 -> 6000 | K38: =J38+H38 -> 10000 | L38: =J38*$N$4+H38*$M$4 -> 12280
B39: =B33+1 -> 6 | C39: 6. REVESTIMENTOS DE PISO E PAREDES | F39: =K39/$K$55 -> 0.064212658 | H39: =SUM(H40:H44) -> 4295.46 | J39: =SUM(J40:J44) -> 11719.12 | K39: =J39+H39 -> 16014.58 | L39: =J39*$N$4+H39*$M$4 -> 19940.253 | Q39: =J39*$R$4 -> 15000.474 | R39: =H39*$Q$4 -> 4939.779
C40: 6.1 ASSENTAMENTO DE PORCELANATO | D40: =1.2*(35.83+7.61) -> 52.128 | E40: M² | F40: =K40/$K$55 -> 0.029052998 | G40: 39 | H40: =G40*D40 -> 2032.992 | I40: 100 | J40: =I40*D40 -> 5212.8 | K40: =J40+H40 -> 7245.792 | L40: =J40*$N$4+H40*$M$4 -> 9010.3248 | Q40: =J40*$R$4 -> 6672.384 | R40: =H40*$Q$4 -> 2337.9408
C41: 6.2 ASSENTAMENTO DE PASTILHAS | D41: =1.2*(10.33+1.79+6.5+1.06) -> 23.616 | E41: M² | F41: =K41/$K$55 -> 0.013162132 | G41: 39 | H41: =D41*G41 -> 921.024 | I41: 100 | J41: =I41*D41 -> 2361.6 | K41: =J41+H41 -> 3282.624 | L41: =J41*$N$4+H41*$M$4 -> 4082.0256 | Q41: =J41*$R$4 -> 3022.848 | R41: =H41*$Q$4 -> 1059.1776
C42: 6.3 ASSENTAMENTO LADRILHO HIDRÁULICO | D42: =1.2*(1.62+6.71) -> 9.996 | E42: M² | F42: =K42/$K$55 -> 0.0055711665 | G42: 39 | H42: =D42*G42 -> 389.844 | I42: 100 | J42: =I42*D42 -> 999.6 | K42: =J42+H42 -> 1389.444 | L42: =J42*$N$4+H42*$M$4 -> 1727.8086 | Q42: =J42*$R$4 -> 1279.488 | R42: =H42*$Q$4 -> 448.3206
C43: 6.4 REVESTIMENTOS EM TIJOLOS MACIÇOS | D43: =1.2*6.72 -> 8.064 | E43: M | F43: =K43/$K$55 -> 0.0033950401 | G43: 25 | H43: =D43*G43 -> 201.6 | I43: 80 | J43: =I43*D43 -> 645.12 | K43: =J43+H43 -> 846.72 | L43: =J43*$N$4+H43*$M$4 -> 1057.5936
C44: 6.5 INSTALAÇÃO DE RODAPÉS | D44: 1 | E44: VB | F44: =K44/$K$55 -> 0.013031321 | G44: 750 | H44: =D44*G44 -> 750 | I44: 2500 | J44: =I44*D44 -> 2500 | K44: =J44+H44 -> 3250 | L44: =J44*$N$4+H44*$M$4 -> 4062.5
B45: =B39+1 -> 7 | C45: 7. ESQUADRIAS | F45: =K45/$K$55 -> 0.012630358 | H45: =SUM(H46) -> 750 | J45: =SUM(J46) -> 2400 | K45: =J45+H45 -> 3150 | L45: =J45*$N$4+H45*$M$4 -> 3934.5
C46: 7.1 INSTALAÇÕES DE PORTAS | D46: 6 | E46: UNIDADE | F46: =K46/$K$55 -> 0.012630358 | G46: 125 | H46: =D46*G46 -> 750 | I46: 400 | J46: =I46*D46 -> 2400 | K46: =J46+H46 -> 3150 | L46: =J46*$N$4+H46*$M$4 -> 3934.5
B47: =B45+1 -> 8 | C47: 8. LOUÇAS E METAIS E ACABAMENTOS ELÉTRICOS | F47: =K47/$K$55 -> 0.037337743 | H47: =SUM(H48:H49) -> 2320 | J47: =SUM(J48:J49) -> 6992 | K47: =J47+H47 -> 9312 | L47: =J47*$N$4+H47*$M$4 -> 11617.76
C48: 8.1 INSTALAÇÕES DE LOUÇAS E METAIS | D48: 25 | E48: UNIDADE | F48: =K48/$K$55 -> 0.009021684 | G48: 50 | H48: =D48*G48 -> 1250 | I48: 40 | J48: =I48*D48 -> 1000 | K48: =J48+H48 -> 2250 | L48: =J48*$N$4+H48*$M$4 -> 2717.5
C49: 8.2 INSTALAÇÃO DE ACABAMENTOS ELÉTRICOS | D49: =161+53 -> 214 | E49: UNIDADE | F49: =K49/$K$55 -> 0.028316059 | G49: 5 | H49: =D49*G49 -> 1070 | I49: 28 | J49: =I49*D49 -> 5992 | K49: =J49+H49 -> 7062 | L49: =J49*$N$4+H49*$M$4 -> 8900.26
B50: =B47+1 -> 9 | C50: 9. PINTURA | F50: =K50/$K$55 -> 0.11082489 | H50: =SUM(H51:H54) -> 11040.864 | J50: =SUM(J51:J54) -> 16598.766 | K50: =J50+H50 -> 27639.63 | L50: =J50*$N$4+H50*$M$4 -> 33943.414
C51: 9.1 PINTURA ACRÍLICA BRANCA | D51: =(52.45+24.71+11.45+36.09)*1.2 -> 149.64 | E51: M² | F51: =K51/$K$55 -> 0.024000085 | G51: 15 | H51: =D51*G51 -> 2244.6 | I51: 25 | J51: =I51*D51 -> 3741 | K51: =J51+H51 -> 5985.6 | L51: =J51*$N$4+H51*$M$4 -> 7369.77
C52: 9.2 PINTURA DE COR | D52: =(59.96+8.7+9.29+1.61+15.21+0.46+3.74+4.17+6.94+3.54+20.03+(2.34+3.11+1.51*2+1.35*2)*2.7)*1.2 -> 196.5708 | E52: M² | F52: =K52/$K$55 -> 0.059113321 | G52: 30 | H52: =D52*G52 -> 5897.124 | I52: 45 | J52: =I52*D52 -> 8845.686 | K52: =J52+H52 -> 14742.81 | L52: =J52*$N$4+H52*$M$4 -> 18104.171
C53: 9.3 APLICAÇÃO DE TEXTURA | D53: =70.99*1.2 -> 85.188 | E53: M² | F53: =K53/$K$55 -> 0.022202244 | G53: 30 | H53: =D53*G53 -> 2555.64 | I53: 35 | J53: =I53*D53 -> 2981.58 | K53: =J53+H53 -> 5537.22 | L53: =J53*$N$4+H53*$M$4 -> 6755.4084
C54: 9.4 APLICAÇÃO DE PAPEL DE PAREDE | D54: =11.45*1.5 -> 17.175 | E54: M² | F54: =K54/$K$55 -> 0.0055092417 | G54: 20 | H54: =D54*G54 -> 343.5 | I54: 60 | J54: =I54*D54 -> 1030.5 | K54: =J54+H54 -> 1374 | L54: =J54*$N$4+H54*$M$4 -> 1714.065
H55: =SUM(H5:H54)/2 -> 86381.576 | J55: =SUM(J5:J54)/2 -> 163017.54 | K55: =SUM(K5:K54)/2 -> 249399.11 | L55: =SUM(L5:L54)/2 -> 308001.26
L56: =L55-K55 -> 58602.147
L57: =L56/L55 -> 0.19026593
J58: ÁREA | K58: CUSTO | L58: VENDA
J59: =6.14+31.7+13.77+3.51+11.58+4.5+12.16+1.83+50.91+3.33+11.69+11.16+1.65+15+12.32+12.19+2.51 -> 205.95 | K59: =K55/$J$59 -> 1210.9692 | L59: =L55/$J$59 -> 1495.5147
L60: =L59-K59 -> 284.54551
L61: =L60/L59 -> 0.19026593

Sheet Aux
B2: =orçamento!C5 -> 1. MOBILIZAÇÃO E ACOMPANHAMENTO TÉCNICO | C2: =orçamento!C9 -> 2. DEMOLIÇÕES | D2: =orçamento!C19 -> 3. ESTRUTURA E DE CONCRETO ARMADO | E2: =orçamento!C22 -> 4. OBRA CIVIL | F2: =orçamento!C33 -> 5. INSTALAÇÕES | G2: =orçamento!C39 -> 6. REVESTIMENTOS DE PISO E PAREDES | H2: =orçamento!C45 -> 7. ESQUADRIAS | I2: =orçamento!C47 -> 8. LOUÇAS E METAIS E ACABAMENTOS ELÉTRICOS | J2: =orçamento!C50 -> 9. PINTURA
B3: =orçamento!C6 -> 1.1 ACOMPANHAMENTO TÉCNICO | C3: =orçamento!C10 -> 2.1 DEMOLIÇÃO DE ALVENARIA | D3: =orçamento!C20 -> 3.1 EXECUÇÃO DE ESCADA DE CONCRETO ARMADO | E3: =orçamento!C23 -> 4.1 INSTALAÇÃO DE FORRO DE GESSO COM TABICAS NOS BANHEIROS | F3: =orçamento!C34 -> 5.1 INSTALAÇÃO HIDRÁULICA | G3: =orçamento!C40 -> 6.1 ASSENTAMENTO DE PORCELANATO | H3: =orçamento!C46 -> 7.1 INSTALAÇÕES DE PORTAS | I3: =orçamento!C48 -> 8.1 INSTALAÇÕES DE LOUÇAS E METAIS | J3: =orçamento!C51 -> 9.1 PINTURA ACRÍLICA BRANCA
B4: =orçamento!C7 -> 1.2 EQUIPAMENTOS, EPIS E EPCS | C4: =orçamento!C11 -> 2.2 DEMOLIÇÃO DE PISO | D4: =orçamento!C21 -> 3.2 EXECUÇÃO DE BANCADA EM CONCRETO | E4: =orçamento!C24 -> 4.2 INSTALAÇÃO DE CORTINEIROS | F4: =orçamento!C35 -> 5.2 INSTALAÇÃO ELÉTRICA | G4: =orçamento!C41 -> 6.2 ASSENTAMENTO DE PASTILHAS | I4: =orçamento!C49 -> 8.2 INSTALAÇÃO DE ACABAMENTOS ELÉTRICOS | J4: =orçamento!C52 -> 9.2 PINTURA DE COR
B5: =orçamento!C8 -> 1.3 OUTROS | C5: =orçamento!C12 -> 2.3 DEMOLIÇÃO DE ESCADA | E5: =orçamento!C25 -> 4.3 ELEVAÇÃO DE DRYWALL | F5: =orçamento!C36 -> 5.3 INSTALAÇÕES ESPECIAIS | G5: =orçamento!C42 -> 6.3 ASSENTAMENTO LADRILHO HIDRÁULICO | J5: =orçamento!C53 -> 9.3 APLICAÇÃO DE TEXTURA
C6: =orçamento!C13 -> 2.4 ABERTURA DE VÃO EM LAJE | E6: =orçamento!C26 -> 4.4 ELEVAÇÃO DE PLACAS CIMENTÍCIAS | F6: =orçamento!C37 -> 5.4 INSTALAÇÃO GÁS | G6: =orçamento!C43 -> 6.4 REVESTIMENTOS EM TIJOLOS MACIÇOS | J6: =orçamento!C54 -> 9.4 APLICAÇÃO DE PAPEL DE PAREDE
C7: =orçamento!C14 -> 2.5 ABERTURA DE RASGOS DIVERSOS EM ALVENARIA E CONTRAPISO | E7: =orçamento!C27 -> 4.5 REQUADRO DE PORTAS E JANELAS | F7: =orçamento!C38 -> 5.5 INSTALAÇÃO DE AR CONDICIONADO | G7: =orçamento!C44 -> 6.5 INSTALAÇÃO DE RODAPÉS
C8: =orçamento!C15 -> 2.6 DEMOLIÇÃO DE REVESTIMENTO DE PAREDE | E8: =orçamento!C28 -> 4.6 CONSTRUÇÃO DE SÓCULOS
C9: =orçamento!C16 -> 2.7 DEMOLIÇÃO DE FORRO | E9: =orçamento!C29 -> 4.7 ELEVAÇÃO DE ALVENARIA
C10: =orçamento!C17 -> 2.8 DEMOLIÇÃO DE LOUÇAS, BANCADAS, MARCENARIA E ESQUADRIAS | E10: =orçamento!C30 -> 4.8 RECUPERAÇÃO DE CONTRAPISO
C11: =orçamento!C18 -> 2.9 BOTA FORA EM CAÇAMBAS LEGAIS | E11: =orçamento!C31 -> 4.9 EXECUÇÃO DE EMBOÇO
E12: =orçamento!C32 -> 4.10 IMPERMEABILIZAÇÃO COM CRISTALIZANTE NOS BANHEIROS
B14: =MID(B2,4,50) -> MOBILIZAÇÃO E ACOMPANHAMENTO TÉCNICO | C14: =MID(C2,4,50) -> DEMOLIÇÕES | D14: =MID(D2,4,50) -> ESTRUTURA E DE CONCRETO ARMADO | E14: =MID(E2,4,50) -> OBRA CIVIL | F14: =MID(F2,4,50) -> INSTALAÇÕES | G14: =MID(G2,4,50) -> REVESTIMENTOS DE PISO E PAREDES | H14: =MID(H2,4,50) -> ESQUADRIAS | I14: =MID(I2,4,50) -> LOUÇAS E METAIS E ACABAMENTOS ELÉTRICOS | J14: =MID(J2,4,50) -> PINTURA
B15: =MID(B3,5,150) -> ACOMPANHAMENTO TÉCNICO | C15: =MID(C3,5,150) -> DEMOLIÇÃO DE ALVENARIA | D15: =MID(D3,5,150) -> EXECUÇÃO DE ESCADA DE CONCRETO ARMADO | E15: =MID(E3,5,150) -> INSTALAÇÃO DE FORRO DE GESSO COM TABICAS NOS BANHEIROS | F15: =MID(F3,5,150) -> INSTALAÇÃO HIDRÁULICA | G15: =MID(G3,5,150) -> ASSENTAMENTO DE PORCELANATO | H15: =MID(H3,5,150) -> INSTALAÇÕES DE PORTAS | I15: =MID(I3,5,150) -> INSTALAÇÕES DE LOUÇAS E METAIS | J15: =MID(J3,5,150) -> PINTURA ACRÍLICA BRANCA
B16: =MID(B4,5,150) -> EQUIPAMENTOS, EPIS E EPCS | C16: =MID(C4,5,150) -> DEMOLIÇÃO DE PISO | D16: =MID(D4,5,150) -> EXECUÇÃO DE BANCADA EM CONCRETO | E16: =MID(E4,5,150) -> INSTALAÇÃO DE CORTINEIROS | F16: =MID(F4,5,150) -> INSTALAÇÃO ELÉTRICA | G16: =MID(G4,5,150) -> ASSENTAMENTO DE PASTILHAS | H16: =MID(H4,5,150) | I16: =MID(I4,5,150) -> INSTALAÇÃO DE ACABAMENTOS ELÉTRICOS | J16: =MID(J4,5,150) -> PINTURA DE COR
B17: =MID(B5,5,150) -> OUTROS | C17: =MID(C5,5,150) -> DEMOLIÇÃO DE ESCADA | D17: =MID(D5,5,150) | E17: =MID(E5,5,150) -> ELEVAÇÃO DE DRYWALL | F17: =MID(F5,5,150) -> INSTALAÇÕES ESPECIAIS | G17: =MID(G5,5,150) -> ASSENTAMENTO LADRILHO HIDRÁULICO | H17: =MID(H5,5,150) | I17: =MID(I5,5,150) | J17: =MID(J5,5,150) -> APLICAÇÃO DE TEXTURA
B18: =MID(B6,5,150) | C18: =MID(C6,5,150) -> ABERTURA DE VÃO EM LAJE | D18: =MID(D6,5,150) | E18: =MID(E6,5,150) -> ELEVAÇÃO DE PLACAS CIMENTÍCIAS | F18: =MID(F6,5,150) -> INSTALAÇÃO GÁS | G18: =MID(G6,5,150) -> REVESTIMENTOS EM TIJOLOS MACIÇOS | H18: =MID(H6,5,150) | I18: =MID(I6,5,150) | J18: =MID(J6,5,150) -> APLICAÇÃO DE PAPEL DE PAREDE
B19: =MID(B7,5,150) | C19: =MID(C7,5,150) -> ABERTURA DE RASGOS DIVERSOS EM ALVENARIA E CONTRAPISO | D19: =MID(D7,5,150) | E19: =MID(E7,5,150) -> REQUADRO DE PORTAS E JANELAS | F19: =MID(F7,5,150) -> INSTALAÇÃO DE AR CONDICIONADO | G19: =MID(G7,5,150) -> INSTALAÇÃO DE RODAPÉS | H19: =MID(H7,5,150) | I19: =MID(I7,5,150) | J19: =MID(J7,5,150)
B20: =MID(B8,5,150) | C20: =MID(C8,5,150) -> DEMOLIÇÃO DE REVESTIMENTO DE PAREDE | D20: =MID(D8,5,150) | E20: =MID(E8,5,150) -> CONSTRUÇÃO DE SÓCULOS | F20: =MID(F8,5,150) | G20: =MID(G8,5,150) | H20: =MID(H8,5,150) | I20: =MID(I8,5,150) | J20: =MID(J8,5,150)
B21: =MID(B9,5,150) | C21: =MID(C9,5,150) -> DEMOLIÇÃO DE FORRO | D21: =MID(D9,5,150) | E21: =MID(E9,5,150) -> ELEVAÇÃO DE ALVENARIA | F21: =MID(F9,5,150) | G21: =MID(G9,5,150) | H21: =MID(H9,5,150) | I21: =MID(I9,5,150) | J21: =MID(J9,5,150)
B22: =MID(B10,5,150) | C22: =MID(C10,5,150) -> DEMOLIÇÃO DE LOUÇAS, BANCADAS, MARCENARIA E ESQUADRIAS | D22: =MID(D10,5,150) | E22: =MID(E10,5,150) -> RECUPERAÇÃO DE CONTRAPISO | F22: =MID(F10,5,150) | G22: =MID(G10,5,150) | H22: =MID(H10,5,150) | I22: =MID(I10,5,150) | J22: =MID(J10,5,150)
B23: =MID(B11,5,150) | C23: =MID(C11,5,150) -> BOTA FORA EM CAÇAMBAS LEGAIS | D23: =MID(D11,5,150) | E23: =MID(E11,5,150) -> EXECUÇÃO DE EMBOÇO | F23: =MID(F11,5,150) | G23: =MID(G11,5,150) | H23: =MID(H11,5,150) | I23: =MID(I11,5,150) | J23: =MID(J11,5,150)
B24: =MID(B12,5,150) | C24: =MID(C12,5,150) | D24: =MID(D12,5,150) | E24: =MID(E12,5,150) -> IMPERMEABILIZAÇÃO COM CRISTALIZANTE NOS BANHEIROS | F24: =MID(F12,5,150) | G24: =MID(G12,5,150) | H24: =MID(H12,5,150) | I24: =MID(I12,5,150) | J24: =MID(J12,5,150)
C25: =MID(C13,5,50) | D25: =MID(D13,5,50) | E25: =MID(E13,5,50) | F25: =MID(F13,5,50) | G25: =MID(G13,5,50) | H25: =MID(H13,5,50) | I25: =MID(I13,5,50) | J25: =MID(J13,5,50)

Sheet resumo
C2: PLANEJADO | D2: REAL | E2: DIFERENÇA | F2: CUSTO REAL / M² | G2: % CUSTO REAL / M²
B3: VENDA TOTAL | C3: =orçamento!L55 -> 308001.26 | E3: =D3-C3 -> -308001.26 | F3: =D3/orçamento!$L$2 -> #DIV/0!
B4: CUSTO TOTAL | C4: =SUM(C5:C14) -> 249399.11 | D4: =SUM(D5:D14) -> 100995.31 | E4: =D4-C4 -> -148403.8 | F4: =D4/orçamento!$L$2 -> #DIV/0!
B5: MÃO DE OBRA | C5: =orçamento!J55 -> 163017.54 | D5: =SUMIF(lançamentos!E:E,"MDO",lançamentos!I:I) -> 46261.9 | E5: =D5-C5 -> -116755.64 | F5: =D5/orçamento!$L$2 -> #DIV/0! | G5: =F5/$F$4 -> #DIV/0!
B6: =MID(orçamento!C5,4,150) -> MOBILIZAÇÃO E ACOMPANHAMENTO TÉCNICO | C6: =orçamento!H5 -> 11000 | D6: =SUMIFS(lançamentos!I:I,lançamentos!F:F,resumo!B6,lançamentos!E:E,"MAT") -> 4927.65 | E6: =D6-C6 -> -6072.35 | F6: =D6/orçamento!$L$2 -> #DIV/0! | G6: =F6/$F$4 -> #DIV/0!
B7: =MID(orçamento!C9,4,150) -> DEMOLIÇÕES | C7: =orçamento!H9 -> 8583.6175 | D7: =SUMIFS(lançamentos!I:I,lançamentos!F:F,resumo!B7,lançamentos!E:E,"MAT") -> 2125 | E7: =D7-C7 -> -6458.6175 | F7: =D7/orçamento!$L$2 -> #DIV/0! | G7: =F7/$F$4 -> #DIV/0!
B8: =MID(orçamento!C19,4,150) -> ESTRUTURA E DE CONCRETO ARMADO | C8: =orçamento!H19 -> 3750 | D8: =SUMIFS(lançamentos!I:I,lançamentos!F:F,resumo!B8,lançamentos!E:E,"MAT") -> 3546.21 | E8: =D8-C8 -> -203.79 | F8: =D8/orçamento!$L$2 -> #DIV/0! | G8: =F8/$F$4 -> #DIV/0!
B9: =MID(orçamento!C22,4,150) -> OBRA CIVIL | C9: =orçamento!H22 -> 23491.634 | D9: =SUMIFS(lançamentos!I:I,lançamentos!F:F,resumo!B9,lançamentos!E:E,"MAT") -> 16899.44 | E9: =D9-C9 -> -6592.194 | F9: =D9/orçamento!$L$2 -> #DIV/0! | G9: =F9/$F$4 -> #DIV/0!
B10: =MID(orçamento!C33,4,150) -> INSTALAÇÕES | C10: =orçamento!H33 -> 21150 | D10: =SUMIFS(lançamentos!I:I,lançamentos!F:F,resumo!B10,lançamentos!E:E,"MAT") -> 22849.59 | E10: =D10-C10 -> 1699.59 | F10: =D10/orçamento!$L$2 -> #DIV/0! | G10: =F10/$F$4 -> #DIV/0!
B11: =MID(orçamento!C39,4,150) -> REVESTIMENTOS DE PISO E PAREDES | C11: =orçamento!H39 -> 4295.46 | D11: =SUMIFS(lançamentos!I:I,lançamentos!F:F,resumo!B11,lançamentos!E:E,"MAT") -> 726.75 | E11: =D11-C11 -> -3568.71 | F11: =D11/orçamento!$L$2 -> #DIV/0! | G11: =F11/$F$4 -> #DIV/0!
B12: =MID(orçamento!C45,4,150) -> ESQUADRIAS | C12: =orçamento!H45 -> 750 | D12: =SUMIFS(lançamentos!I:I,lançamentos!F:F,resumo!B12,lançamentos!E:E,"MAT") -> 0 | E12: =D12-C12 -> -750 | F12: =D12/orçamento!$L$2 -> #DIV/0! | G12: =F12/$F$4 -> #DIV/0!
B13: =MID(orçamento!C47,4,150) -> LOUÇAS E METAIS E ACABAMENTOS ELÉTRICOS | C13: =orçamento!H47 -> 2320 | D13: =SUMIFS(lançamentos!I:I,lançamentos!F:F,resumo!B13,lançamentos!E:E,"MAT") -> 0 | E13: =D13-C13 -> -2320 | F13: =D13/orçamento!$L$2 -> #DIV/0! | G13: =F13/$F$4 -> #DIV/0!
B14: =MID(orçamento!C50,4,150) -> PINTURA | C14: =orçamento!H50 -> 11040.864 | D14: =SUMIFS(lançamentos!I:I,lançamentos!F:F,resumo!B14,lançamentos!E:E,"MAT") -> 3658.77 | E14: =D14-C14 -> -7382.094 | F14: =D14/orçamento!$L$2 -> #DIV/0! | G14: =F14/$F$4 -> #DIV/0!
B15: SALDO TOTAL | C15: =C3-C4 -> 58602.147 | D15: =D3-D4 -> -100995.31 | E15: =E3-E4 -> -159597.46
